aida_notifications/__init__.py
aida_notifications/admin.py
aida_notifications/apps.py
aida_notifications/models.py
aida_notifications/service.py
aida_notifications/settings.py
aida_notifications/signals.py
aida_notifications/backends/__init__.py
aida_notifications/backends/base.py
aida_notifications/backends/email.py
aida_notifications/backends/sms.py
aida_notifications/management/__init__.py
aida_notifications/management/commands/__init__.py
aida_notifications/management/commands/create_sample_templates.py
aida_notifications/management/commands/test_notification.py
aida_notifications/migrations/0001_initial.py
aida_notifications/migrations/__init__.py
django_aida_notifications-1.0.0.dist-info/licenses/LICENSE
django_aida_notifications-1.0.0.dist-info/METADATA
django_aida_notifications-1.0.0.dist-info/WHEEL
django_aida_notifications-1.0.0.dist-info/top_level.txt
django_aida_notifications-1.0.0.dist-info/RECORD
