Metadata-Version: 2.4
Name: django-aida-notifications
Version: 1.0.0
Summary: A comprehensive Django notification extension with email (via Anymail) and SMS (via Twilio) support
Home-page: https://github.com/hmesfin/aida-notifications
Author: AIDA Notifications Contributors
Author-email: AIDA Notifications Contributors <support@aida-notifications.org>
Maintainer-email: AIDA Team <maintainers@aida-notifications.org>
License: MIT
Project-URL: Homepage, https://github.com/hmesfin/aida-notifications
Project-URL: Documentation, https://github.com/hmesfin/aida-notifications#readme
Project-URL: Repository, https://github.com/hmesfin/aida-notifications.git
Project-URL: Bug Tracker, https://github.com/hmesfin/aida-notifications/issues
Project-URL: Changelog, https://github.com/hmesfin/aida-notifications/blob/main/CHANGELOG.md
Keywords: django,notifications,email,sms,twilio,anymail
Classifier: Development Status :: 4 - Beta
Classifier: Intended Audience :: Developers
Classifier: License :: OSI Approved :: MIT License
Classifier: Operating System :: OS Independent
Classifier: Programming Language :: Python
Classifier: Programming Language :: Python :: 3
Classifier: Programming Language :: Python :: 3.8
Classifier: Programming Language :: Python :: 3.9
Classifier: Programming Language :: Python :: 3.10
Classifier: Programming Language :: Python :: 3.11
Classifier: Programming Language :: Python :: 3.12
Classifier: Framework :: Django
Classifier: Framework :: Django :: 3.2
Classifier: Framework :: Django :: 4.0
Classifier: Framework :: Django :: 4.1
Classifier: Framework :: Django :: 4.2
Classifier: Framework :: Django :: 5.0
Classifier: Framework :: Django :: 5.1
Classifier: Topic :: Communications :: Email
Classifier: Topic :: Communications :: Telephony
Classifier: Topic :: Software Development :: Libraries :: Python Modules
Requires-Python: >=3.8
License-File: LICENSE
Requires-Dist: Django<6.0,>=3.2
Requires-Dist: django-anymail>=8.0
Requires-Dist: twilio>=7.0
Provides-Extra: dev
Requires-Dist: pytest>=7.0; extra == "dev"
Requires-Dist: pytest-django>=4.0; extra == "dev"
Requires-Dist: pytest-cov>=3.0; extra == "dev"
Requires-Dist: ruff>=0.1.0; extra == "dev"
Requires-Dist: mypy>=0.950; extra == "dev"
Requires-Dist: django-stubs>=1.12.0; extra == "dev"
Requires-Dist: pre-commit>=3.0; extra == "dev"
Provides-Extra: redis
Requires-Dist: redis>=4.0; extra == "redis"
Requires-Dist: django-redis>=5.0; extra == "redis"
Provides-Extra: celery
Requires-Dist: celery>=5.0; extra == "celery"
Dynamic: author
Dynamic: home-page
Dynamic: license-file
Dynamic: requires-python
